number_theory_primes-0.1.2.dist-info/licenses/LICENSE
primes/__init__.py
primes/aks/__init__.py
primes/aks/core.py
primes/utils/__init__.py
primes/utils/math_utils.py
primes/utils/polynomial.py
number_theory_primes-0.1.2.dist-info/METADATA
number_theory_primes-0.1.2.dist-info/WHEEL
number_theory_primes-0.1.2.dist-info/top_level.txt
number_theory_primes-0.1.2.dist-info/RECORD
